pagination/__init__.py
pagination/middleware.py
pagination/models.py
paginate_fastapi-0.1.0.dist-info/LICENSE
paginate_fastapi-0.1.0.dist-info/METADATA
paginate_fastapi-0.1.0.dist-info/WHEEL
paginate_fastapi-0.1.0.dist-info/RECORD
