Metadata-Version: 2.3
Name: paginate-fastapi
Version: 0.1.0
Summary: A simple and efficient pagination library for FastAPI applications
License: MIT
Keywords: fastapi,sqlmodel,pagination,async,filtering,sorting
Author: Ritvik Dayal
Author-email: ritvikr1605@gmail.com
Requires-Python: >=3.11
Classifier: Development Status :: 4 - Beta
Classifier: Framework :: FastAPI
Classifier: Intended Audience :: Developers
Classifier: License :: OSI Approved :: MIT License
Classifier: Operating System :: OS Independent
Classifier: Programming Language :: Python :: 3
Classifier: Programming Language :: Python :: 3.11
Classifier: Topic :: Software Development :: Libraries :: Python Modules
Classifier: Typing :: Typed
Provides-Extra: dev
Requires-Dist: aiosqlite (>=0.20.0) ; extra == "dev"
Requires-Dist: black (>=24.1.0) ; extra == "dev"
Requires-Dist: fastapi (>=0.100.0)
Requires-Dist: fastapi[all] (>=0.100.0) ; extra == "dev"
Requires-Dist: httpx (>=0.27.0) ; extra == "dev"
Requires-Dist: mypy (>=1.8.0) ; extra == "dev"
Requires-Dist: pre-commit (>=4.1.0,<5.0.0)
Requires-Dist: pydantic (>=2.0.0)
Requires-Dist: pytest (>=8.0.0) ; extra == "dev"
Requires-Dist: pytest-asyncio (>=0.23.0) ; extra == "dev"
Requires-Dist: pytest-cov (>=4.1.0) ; extra == "dev"
Requires-Dist: ruff (>=0.9.7,<0.10.0) ; extra == "dev"
Requires-Dist: sqlmodel (>=0.0.8)
Project-URL: Documentation, https://github.com/ritvikdayal/paginate-fastapi#readme
Project-URL: Homepage, https://github.com/ritvikdayal/paginate-fastapi
Project-URL: Issues, https://github.com/ritvikdayal/paginate-fastapi/issues
Project-URL: Repository, https://github.com/ritvikdayal/paginate-fastapi.git
